[{"period":{"endDate":"2022-08-31","timeZone":null,"startTime":"00:00:00","endTime":"23:59:00","startDate":"2022-07-01"},"financeStatus":{"financeLineStatus":"CLOSED"},"lastModifiedDate":"2022-10-22,02:27:18 PM","lastModifiedBy":"external_system@digitalsandbox04.com","rates":{"ucbdwp":12,"unitTypeId":"783r_cPNRWymzGk1TAA1cA","netUnitCostBelowFloorPrice":true,"quantity":23000,"netCost":276,"suggestedBuffer":0,"costMethodId":"0v2s85VAQ26PNifBbFyqCA","grossCost":276,"netUnitCostBelowGoalPrice":false,"ucbd":12,"productionQuantity":23000,"grossUnitCost":12,"netUnitCost":12,"rcPrices":{"floorPrice":14,"goalPrice":12,"ratecardPrice":10},"productionBuffer":0,"discounts":[{"discountName":"Added Value","gross":false,"sortOrder":1,"discountType":"Other","discountValue":0},{"discountName":"Other Discouint","gross":true,"sortOrder":2,"discountType":"Other","discountValue":0},{"discountName":"Other Discouint","gross":false,"sortOrder":3,"discountType":"Agency","discountValue":0}],"lineValue":276,"totalDiscount":0,"sov":100,"ucbdBelowGoalPrice":false,"grossDiscount":0},"description":null,"orderStatus":{"pushState":null,"sentToOrder":null,"salesLineStatus":"CLOSED"},"distribution":"Pro-rate by Day","sequenceId":1079,"version":1,"planWorkspaceProduct":{"ratecard":{"ratecardId":"6231c070184d7c2c3332fd19","asOfDate":"2022-06-06,04:38:39 PM"},"lineNo":"1","productId":"62263f5569df880da88f504e","lineClassAttributes":{"canExport":true,"guaranteedAudience":0,"planRate":1,"canInvoice":true,"guaranteedRate":0,"canProduce":true,"planAudience":0,"hasPerformance":true},"lineType":"STANDARD","packageLineId":null,"planProductId":"629e2d8eef19313e03ec8cad","lineClassId":"5-bA41eBRj-EuTYRzg-cqA","commercialTypeId":null,"packageType":null},"createdDate":"2022-06-06,04:38:39 PM","customFieldValues":null,"createdBy":"CameliaStefan@digitalsandbox04.com","name":"Lawn Care Review 300x250 |","planId":"629e2cd582cb3e439e6c526c","id":"629e2d8fef19313e03ec8cb0","thirdPartyBillableAdServerId":null,"weightedAllocation":null,"packageChilds":null},{"period":{"endDate":"2022-08-31","timeZone":null,"startTime":"00:00:00","endTime":"23:59:00","startDate":"2022-07-01"},"financeStatus":{"financeLineStatus":"CLOSED"},"lastModifiedDate":"2022-10-22,02:27:18 PM","lastModifiedBy":"external_system@digitalsandbox04.com","rates":{"ucbdwp":22,"unitTypeId":"783r_cPNRWymzGk1TAA1cA","netUnitCostBelowFloorPrice":false,"quantity":450000,"netCost":9900,"suggestedBuffer":0,"costMethodId":"0v2s85VAQ26PNifBbFyqCA","grossCost":9900,"netUnitCostBelowGoalPrice":false,"ucbd":22,"productionQuantity":450000,"grossUnitCost":22,"netUnitCost":22,"rcPrices":{"floorPrice":16,"goalPrice":22,"ratecardPrice":18.25},"productionBuffer":0,"discounts":[{"discountName":"Added Value","gross":false,"sortOrder":1,"discountType":"Other","discountValue":0},{"discountName":"Other Discouint","gross":true,"sortOrder":2,"discountType":"Other","discountValue":0},{"discountName":"Other Discouint","gross":false,"sortOrder":3,"discountType":"Agency","discountValue":0}],"lineValue":9900,"totalDiscount":0,"sov":100,"ucbdBelowGoalPrice":false,"grossDiscount":0},"description":null,"orderStatus":{"pushState":null,"sentToOrder":null,"salesLineStatus":"CLOSED"},"distribution":"Pro-rate by Day","sequenceId":1080,"version":1,"planWorkspaceProduct":{"ratecard":{"ratecardId":"6231c070184d7c2c3332fd19","asOfDate":"2022-06-06,04:38:39 PM"},"lineNo":"2","productId":"62263bae4293570c656263b3","lineClassAttributes":{"canExport":true,"guaranteedAudience":0,"planRate":1,"canInvoice":true,"guaranteedRate":0,"canProduce":true,"planAudience":0,"hasPerformance":true},"lineType":"STANDARD","packageLineId":null,"planProductId":"629e2d8eef19313e03ec8caf","lineClassId":"5-bA41eBRj-EuTYRzg-cqA","commercialTypeId":null,"packageType":null},"createdDate":"2022-06-06,04:38:39 PM","customFieldValues":null,"createdBy":"CameliaStefan@digitalsandbox04.com","name":"Lawn Care Review Pre-Roll Video 30 Sec |","planId":"629e2cd582cb3e439e6c526c","id":"629e2d8fef19313e03ec8cb1","thirdPartyBillableAdServerId":null,"weightedAllocation":null,"packageChilds":null},{"period":{"endDate":"2022-08-31","timeZone":null,"startTime":"00:00:00","endTime":"23:59:00","startDate":"2022-07-01"},"financeStatus":{"financeLineStatus":"CLOSED"},"lastModifiedDate":"2022-10-22,02:27:18 PM","lastModifiedBy":"external_system@digitalsandbox04.com","rates":{"ucbdwp":22,"unitTypeId":"783r_cPNRWymzGk1TAA1cA","netUnitCostBelowFloorPrice":false,"quantity":500000,"netCost":8934.75,"suggestedBuffer":0,"costMethodId":"0v2s85VAQ26PNifBbFyqCA","grossCost":9405,"netUnitCostBelowGoalPrice":true,"ucbd":22,"productionQuantity":500000,"grossUnitCost":18.81,"netUnitCost":17.87,"rcPrices":{"floorPrice":15,"goalPrice":22,"ratecardPrice":10},"productionBuffer":0,"discounts":[{"discountName":"Added Value","gross":false,"sortOrder":1,"discountType":"Other","discountValue":10},{"discountName":"Other Discouint","gross":true,"sortOrder":2,"discountType":"Other","discountValue":5},{"discountName":"Other Discouint","gross":false,"sortOrder":3,"discountType":"Agency","discountValue":5}],"lineValue":8934.75,"totalDiscount":18.775,"sov":100,"ucbdBelowGoalPrice":false,"grossDiscount":0},"description":null,"orderStatus":{"pushState":null,"sentToOrder":null,"salesLineStatus":"CLOSED"},"distribution":"Pro-rate by Day","sequenceId":1081,"version":1,"planWorkspaceProduct":{"ratecard":{"ratecardId":"6231c070184d7c2c3332fd19","asOfDate":"2022-06-06,04:38:39 PM"},"lineNo":"3","productId":"62263f3e69df880da88f504d","lineClassAttributes":{"canExport":true,"guaranteedAudience":0,"planRate":1,"canInvoice":true,"guaranteedRate":0,"canProduce":true,"planAudience":0,"hasPerformance":true},"lineType":"STANDARD","packageLineId":null,"planProductId":"629e2d8eef19313e03ec8cae","lineClassId":"5-bA41eBRj-EuTYRzg-cqA","commercialTypeId":null,"packageType":null},"createdDate":"2022-06-06,04:38:39 PM","customFieldValues":null,"createdBy":"CameliaStefan@digitalsandbox04.com","name":"Lawn Care Review 728x90-|","planId":"629e2cd582cb3e439e6c526c","id":"629e2d8fef19313e03ec8cb2","thirdPartyBillableAdServerId":null,"weightedAllocation":null,"packageChilds":null}]
